pastebin_archiver/__init__.py
pastebin_archiver/__main__.py
pastebin_archiver/api.py
pastebin_archiver/config.py
pastebin_archiver/database.py
pastebin_archiver/event_queue.py
pastebin_archiver/models.py
pastebin_archiver/pastebin_archiver.py
pastebin_archiver-0.2.1.dist-info/entry_points.txt
pastebin_archiver-0.2.1.dist-info/LICENSE
pastebin_archiver-0.2.1.dist-info/WHEEL
pastebin_archiver-0.2.1.dist-info/METADATA
pastebin_archiver-0.2.1.dist-info/RECORD
