Metadata-Version: 2.1
Name: pastebin-archiver
Version: 0.2.1
Summary: Archive all public posts from Pastebin.com
Home-page: https://gitlab.com/jonpavelich/pastebin-archiver
License: MIT
Author: Jon Pavelich
Author-email: pypi@jonpavelich.com
Requires-Python: >=3.7,<4.0
Classifier: License :: OSI Approved :: MIT License
Classifier: Programming Language :: Python :: 3
Classifier: Programming Language :: Python :: 3.7
Classifier: Programming Language :: Python :: 3.8
Provides-Extra: mssql
Provides-Extra: mysql
Provides-Extra: pgsql
Requires-Dist: apscheduler (>=3.6,<4.0)
Requires-Dist: psycopg2 (>=2.8,<3.0); extra == "pgsql"
Requires-Dist: pymysql (>=0.9.3,<0.10.0); extra == "mysql"
Requires-Dist: pyodbc (>=4.0,<5.0); extra == "mssql"
Requires-Dist: requests (>=2.22,<3.0)
Requires-Dist: sqlalchemy (>=1.3,<2.0)
Project-URL: Repository, https://gitlab.com/jonpavelich/pastebin-archiver
